tsp/__init__.py
tsp/hello.py
tspnn-1.0.0.dist-info/LICENSE
tspnn-1.0.0.dist-info/METADATA
tspnn-1.0.0.dist-info/WHEEL
tspnn-1.0.0.dist-info/top_level.txt
tspnn-1.0.0.dist-info/RECORD
